{
  "nodes": [
    {
      "id": "shared_styles_catbus_theme",
      "label": "Shared CATBUS CSS Theme (shared_styles.html)",
      "file_type": "code",
      "source_file": "catbus_scripts/shared_styles.html",
      "source_location": null,
      "source_url": null,
      "captured_at": null,
      "author": null,
      "contributor": null
    },
    {
      "id": "stats_dashboard_ui",
      "label": "Stats Dashboard UI (stats_dashboard.html)",
      "file_type": "code",
      "source_file": "catbus_scripts/stats_dashboard.html",
      "source_location": null,
      "source_url": null,
      "captured_at": null,
      "author": null,
      "contributor": null
    },
    {
      "id": "volunteer_dashboard_ui",
      "label": "Personal Volunteer Dashboard UI (volunteer_dashboard.html)",
      "file_type": "code",
      "source_file": "catbus_scripts/volunteer_dashboard.html",
      "source_location": null,
      "source_url": null,
      "captured_at": null,
      "author": null,
      "contributor": null
    },
    {
      "id": "volunteer_management_ui",
      "label": "Volunteer Management UI (volunteer_management.html)",
      "file_type": "code",
      "source_file": "catbus_scripts/volunteer_management.html",
      "source_location": null,
      "source_url": null,
      "captured_at": null,
      "author": null,
      "contributor": null
    },
    {
      "id": "volunteer_schedule_dashboard_ui",
      "label": "Schedule by Day Dashboard UI (volunteer_schedule_dashboard.html)",
      "file_type": "code",
      "source_file": "catbus_scripts/volunteer_schedule_dashboard.html",
      "source_location": null,
      "source_url": null,
      "captured_at": null,
      "author": null,
      "contributor": null
    },
    {
      "id": "volunteer_signinout_ui",
      "label": "Volunteer Sign-In/Sign-Out UI (volunteer_signinout.html)",
      "file_type": "code",
      "source_file": "catbus_scripts/volunteer_signinout.html",
      "source_location": null,
      "source_url": null,
      "captured_at": null,
      "author": null,
      "contributor": null
    },
    {
      "id": "webpage_faq",
      "label": "Public FAQ Page (FAQ.html)",
      "file_type": "document",
      "source_file": "webpage/FAQ.html",
      "source_location": null,
      "source_url": "https://taxclinic.uwaterloo.ca/FAQ.html",
      "captured_at": null,
      "author": null,
      "contributor": null
    },
    {
      "id": "webpage_postfiling",
      "label": "Post Tax Return Filing Guide (PostFiling.html)",
      "file_type": "document",
      "source_file": "webpage/PostFiling.html",
      "source_location": null,
      "source_url": "https://taxclinic.uwaterloo.ca/PostFiling.html",
      "captured_at": null,
      "author": null,
      "contributor": null
    },
    {
      "id": "webpage_about",
      "label": "About Us Page (about.html)",
      "file_type": "document",
      "source_file": "webpage/about.html",
      "source_location": null,
      "source_url": "https://taxclinic.uwaterloo.ca/about.html",
      "captured_at": null,
      "author": null,
      "contributor": null
    },
    {
      "id": "webpage_admin",
      "label": "Admin Management Tools Portal (admin.html)",
      "file_type": "document",
      "source_file": "webpage/admin.html",
      "source_location": null,
      "source_url": "https://taxclinic.uwaterloo.ca/admin.html",
      "captured_at": null,
      "author": null,
      "contributor": null
    },
    {
      "id": "webpage_appointment_screening",
      "label": "Appointment Eligibility Screening Tool (appointment_screening.html)",
      "file_type": "code",
      "source_file": "webpage/appointment_screening.html",
      "source_location": null,
      "source_url": null,
      "captured_at": null,
      "author": null,
      "contributor": null
    },
    {
      "id": "webpage_catbus",
      "label": "CATBUS Tool Hub (catbus.html)",
      "file_type": "document",
      "source_file": "webpage/catbus.html",
      "source_location": null,
      "source_url": "https://taxclinic.uwaterloo.ca/catbus.html",
      "captured_at": null,
      "author": null,
      "contributor": null
    },
    {
      "id": "webpage_checklist",
      "label": "Tax Return Checklist (checklist.html)",
      "file_type": "document",
      "source_file": "webpage/checklist.html",
      "source_location": null,
      "source_url": "https://taxclinic.uwaterloo.ca/checklist.html",
      "captured_at": null,
      "author": null,
      "contributor": null
    },
    {
      "id": "webpage_feedback",
      "label": "Client Feedback Form (feedback.html)",
      "file_type": "code",
      "source_file": "webpage/feedback.html",
      "source_location": null,
      "source_url": "https://taxclinic.uwaterloo.ca/feedback.html",
      "captured_at": null,
      "author": null,
      "contributor": null
    },
    {
      "id": "webpage_index",
      "label": "Tax Clinic Homepage / Clinic Schedule (index.html)",
      "file_type": "document",
      "source_file": "webpage/index.html",
      "source_location": null,
      "source_url": "https://taxclinic.uwaterloo.ca",
      "captured_at": null,
      "author": null,
      "contributor": null
    },
    {
      "id": "webpage_search",
      "label": "Site Search Page (search.html)",
      "file_type": "code",
      "source_file": "webpage/search.html",
      "source_location": null,
      "source_url": "https://taxclinic.uwaterloo.ca/search.html",
      "captured_at": null,
      "author": null,
      "contributor": null
    },
    {
      "id": "webpage_training",
      "label": "Volunteer Training Documents Page (training.html)",
      "file_type": "document",
      "source_file": "webpage/training.html",
      "source_location": null,
      "source_url": "https://taxclinic.uwaterloo.ca/training.html",
      "captured_at": null,
      "author": null,
      "contributor": null
    },
    {
      "id": "webpage_volunteer_feedback",
      "label": "Volunteer Feedback Form (volunteer_feedback.html)",
      "file_type": "code",
      "source_file": "webpage/volunteer_feedback.html",
      "source_location": null,
      "source_url": "https://taxclinic.uwaterloo.ca/volunteer_feedback.html",
      "captured_at": null,
      "author": null,
      "contributor": null
    },
    {
      "id": "webpage_volunteerapplications",
      "label": "Volunteer Applications Form (volunteerapplications.html)",
      "file_type": "code",
      "source_file": "webpage/volunteerapplications.html",
      "source_location": null,
      "source_url": "https://taxclinic.uwaterloo.ca/volunteerapplications.html",
      "captured_at": null,
      "author": null,
      "contributor": null
    },
    {
      "id": "appsscript_json_config",
      "label": "Apps Script Project Manifest (appsscript.json)",
      "file_type": "code",
      "source_file": "catbus_scripts/appsscript.json",
      "source_location": null,
      "source_url": null,
      "captured_at": null,
      "author": null,
      "contributor": null
    },
    {
      "id": "logo_afsa",
      "label": "AFSA Logo Image (logo.png)",
      "file_type": "image",
      "source_file": "webpage/images/logo.png",
      "source_location": null,
      "source_url": null,
      "captured_at": null,
      "author": null,
      "contributor": null
    },
    {
      "id": "backend_getAdminDashboardData",
      "label": "Backend: getAdminDashboardData()",
      "file_type": "code",
      "source_file": "catbus_scripts/stats_dashboard.html",
      "source_location": "AdminDashboard.gs (inferred)",
      "source_url": null,
      "captured_at": null,
      "author": null,
      "contributor": null
    },
    {
      "id": "backend_getVolunteerScheduleByName",
      "label": "Backend: getVolunteerScheduleByName()",
      "file_type": "code",
      "source_file": "catbus_scripts/volunteer_dashboard.html",
      "source_location": null,
      "source_url": null,
      "captured_at": null,
      "author": null,
      "contributor": null
    },
    {
      "id": "backend_getVolunteerPersonalStats",
      "label": "Backend: getVolunteerPersonalStats()",
      "file_type": "code",
      "source_file": "catbus_scripts/volunteer_dashboard.html",
      "source_location": null,
      "source_url": null,
      "captured_at": null,
      "author": null,
      "contributor": null
    },
    {
      "id": "backend_getVolunteerCredentialStatus",
      "label": "Backend: getVolunteerCredentialStatus()",
      "file_type": "code",
      "source_file": "catbus_scripts/volunteer_dashboard.html",
      "source_location": null,
      "source_url": null,
      "captured_at": null,
      "author": null,
      "contributor": null
    },
    {
      "id": "backend_submitVolunteerCredentials",
      "label": "Backend: submitVolunteerCredentials()",
      "file_type": "code",
      "source_file": "catbus_scripts/volunteer_dashboard.html",
      "source_location": null,
      "source_url": null,
      "captured_at": null,
      "author": null,
      "contributor": null
    },
    {
      "id": "backend_getVolunteerProductKeys",
      "label": "Backend: getVolunteerProductKeys()",
      "file_type": "code",
      "source_file": "catbus_scripts/volunteer_dashboard.html",
      "source_location": null,
      "source_url": null,
      "captured_at": null,
      "author": null,
      "contributor": null
    },
    {
      "id": "backend_getAllVolunteerNames",
      "label": "Backend: getAllVolunteerNames()",
      "file_type": "code",
      "source_file": "catbus_scripts/volunteer_dashboard.html",
      "source_location": null,
      "source_url": null,
      "captured_at": null,
      "author": null,
      "contributor": null
    },
    {
      "id": "backend_getScheduleConfig",
      "label": "Backend: getScheduleConfig()",
      "file_type": "code",
      "source_file": "catbus_scripts/volunteer_dashboard.html",
      "source_location": "Config.gs",
      "source_url": null,
      "captured_at": null,
      "author": null,
      "contributor": null
    },
    {
      "id": "backend_getAcceptedApplications",
      "label": "Backend: getAcceptedApplications()",
      "file_type": "code",
      "source_file": "catbus_scripts/volunteer_management.html",
      "source_location": null,
      "source_url": null,
      "captured_at": null,
      "author": null,
      "contributor": null
    },
    {
      "id": "backend_transferToConsolidatedList",
      "label": "Backend: transferToConsolidatedList()",
      "file_type": "code",
      "source_file": "catbus_scripts/volunteer_management.html",
      "source_location": null,
      "source_url": null,
      "captured_at": null,
      "author": null,
      "contributor": null
    },
    {
      "id": "backend_getVolunteerManagementData",
      "label": "Backend: getVolunteerManagementData()",
      "file_type": "code",
      "source_file": "catbus_scripts/volunteer_management.html",
      "source_location": null,
      "source_url": null,
      "captured_at": null,
      "author": null,
      "contributor": null
    },
    {
      "id": "backend_getNoShowVolunteers",
      "label": "Backend: getNoShowVolunteers()",
      "file_type": "code",
      "source_file": "catbus_scripts/volunteer_management.html",
      "source_location": null,
      "source_url": null,
      "captured_at": null,
      "author": null,
      "contributor": null
    },
    {
      "id": "backend_updateVolunteerRolesBatch",
      "label": "Backend: updateVolunteerRolesBatch()",
      "file_type": "code",
      "source_file": "catbus_scripts/volunteer_management.html",
      "source_location": null,
      "source_url": null,
      "captured_at": null,
      "author": null,
      "contributor": null
    },
    {
      "id": "backend_getUnmatchedVolunteerNames",
      "label": "Backend: getUnmatchedVolunteerNames()",
      "file_type": "code",
      "source_file": "catbus_scripts/volunteer_management.html",
      "source_location": null,
      "source_url": null,
      "captured_at": null,
      "author": null,
      "contributor": null
    },
    {
      "id": "backend_getAlumniData",
      "label": "Backend: getAlumniData()",
      "file_type": "code",
      "source_file": "catbus_scripts/volunteer_management.html",
      "source_location": null,
      "source_url": null,
      "captured_at": null,
      "author": null,
      "contributor": null
    },
    {
      "id": "backend_setVolunteerBlacklist",
      "label": "Backend: setVolunteerBlacklist()",
      "file_type": "code",
      "source_file": "catbus_scripts/volunteer_management.html",
      "source_location": null,
      "source_url": null,
      "captured_at": null,
      "author": null,
      "contributor": null
    },
    {
      "id": "backend_getVolunteerScheduleByDay",
      "label": "Backend: getVolunteerScheduleByDay()",
      "file_type": "code",
      "source_file": "catbus_scripts/volunteer_schedule_dashboard.html",
      "source_location": null,
      "source_url": null,
      "captured_at": null,
      "author": null,
      "contributor": null
    },
    {
      "id": "backend_getVolunteerDistribution",
      "label": "Backend: getVolunteerDistribution()",
      "file_type": "code",
      "source_file": "catbus_scripts/volunteer_schedule_dashboard.html",
      "source_location": null,
      "source_url": null,
      "captured_at": null,
      "author": null,
      "contributor": null
    },
    {
      "id": "backend_getConsolidatedVolunteerData",
      "label": "Backend: getConsolidatedVolunteerData()",
      "file_type": "code",
      "source_file": "catbus_scripts/volunteer_signinout.html",
      "source_location": null,
      "source_url": null,
      "captured_at": null,
      "author": null,
      "contributor": null
    },
    {
      "id": "backend_getAvailableStations",
      "label": "Backend: getAvailableStations()",
      "file_type": "code",
      "source_file": "catbus_scripts/volunteer_signinout.html",
      "source_location": null,
      "source_url": null,
      "captured_at": null,
      "author": null,
      "contributor": null
    },
    {
      "id": "backend_getActiveSessions",
      "label": "Backend: getActiveSessions()",
      "file_type": "code",
      "source_file": "catbus_scripts/volunteer_signinout.html",
      "source_location": null,
      "source_url": null,
      "captured_at": null,
      "author": null,
      "contributor": null
    },
    {
      "id": "backend_getSignInStats",
      "label": "Backend: getSignInStats()",
      "file_type": "code",
      "source_file": "catbus_scripts/volunteer_signinout.html",
      "source_location": null,
      "source_url": null,
      "captured_at": null,
      "author": null,
      "contributor": null
    },
    {
      "id": "backend_signInVolunteer",
      "label": "Backend: signInVolunteer()",
      "file_type": "code",
      "source_file": "catbus_scripts/volunteer_signinout.html",
      "source_location": null,
      "source_url": null,
      "captured_at": null,
      "author": null,
      "contributor": null
    },
    {
      "id": "backend_signOutVolunteer",
      "label": "Backend: signOutVolunteer()",
      "file_type": "code",
      "source_file": "catbus_scripts/volunteer_signinout.html",
      "source_location": null,
      "source_url": null,
      "captured_at": null,
      "author": null,
      "contributor": null
    },
    {
      "id": "concept_eligibility_screening",
      "label": "Eligibility Screening Logic (income/complexity thresholds)",
      "file_type": "document",
      "source_file": "webpage/appointment_screening.html",
      "source_location": null,
      "source_url": null,
      "captured_at": null,
      "author": null,
      "contributor": null
    },
    {
      "id": "concept_volunteer_roles",
      "label": "Volunteer Role System (Filer/Mentor/Frontline/Internal Services)",
      "file_type": "document",
      "source_file": "catbus_scripts/volunteer_management.html",
      "source_location": null,
      "source_url": null,
      "captured_at": null,
      "author": null,
      "contributor": null
    },
    {
      "id": "concept_alumni_blacklist",
      "label": "Volunteer Alumni and Blacklist Management",
      "file_type": "document",
      "source_file": "catbus_scripts/volunteer_management.html",
      "source_location": null,
      "source_url": null,
      "captured_at": null,
      "author": null,
      "contributor": null
    },
    {
      "id": "concept_shared_scripts",
      "label": "Shared Frontend Scripts Include (shared_scripts)",
      "file_type": "code",
      "source_file": "catbus_scripts/volunteer_dashboard.html",
      "source_location": null,
      "source_url": null,
      "captured_at": null,
      "author": null,
      "contributor": null
    },
    {
      "id": "concept_catbus_config_js",
      "label": "Static Config (config.js / CATBUS_CONFIG.WEBAPP_URL)",
      "file_type": "code",
      "source_file": "webpage/catbus.html",
      "source_location": null,
      "source_url": null,
      "captured_at": null,
      "author": null,
      "contributor": null
    },
    {
      "id": "concept_webapp_router",
      "label": "Apps Script Web App Router (?app= dispatch)",
      "file_type": "code",
      "source_file": "webpage/catbus.html",
      "source_location": "catbus_scripts/Router.gs",
      "source_url": null,
      "captured_at": null,
      "author": null,
      "contributor": null
    },
    {
      "id": "concept_google_oauth_scopes",
      "label": "Google OAuth Scopes (Spreadsheets, Drive, Gmail, External)",
      "file_type": "code",
      "source_file": "catbus_scripts/appsscript.json",
      "source_location": null,
      "source_url": null,
      "captured_at": null,
      "author": null,
      "contributor": null
    },
    {
      "id": "concept_password_gate",
      "label": "Password Gate Component (_PasswordGate include)",
      "file_type": "code",
      "source_file": "catbus_scripts/volunteer_management.html",
      "source_location": null,
      "source_url": null,
      "captured_at": null,
      "author": null,
      "contributor": null
    }
  ],
  "edges": [
    {
      "source": "stats_dashboard_ui",
      "target": "shared_styles_catbus_theme",
      "relation": "references",
      "confidence": "EXTRACTED",
      "confidence_score": 1.0,
      "source_file": "catbus_scripts/stats_dashboard.html",
      "source_location": "line 4: <?!= include('shared_styles') ?>",
      "weight": 1.0
    },
    {
      "source": "volunteer_dashboard_ui",
      "target": "shared_styles_catbus_theme",
      "relation": "references",
      "confidence": "EXTRACTED",
      "confidence_score": 1.0,
      "source_file": "catbus_scripts/volunteer_dashboard.html",
      "source_location": "line 5: <?!= include('shared_styles') ?>",
      "weight": 1.0
    },
    {
      "source": "volunteer_schedule_dashboard_ui",
      "target": "shared_styles_catbus_theme",
      "relation": "references",
      "confidence": "EXTRACTED",
      "confidence_score": 1.0,
      "source_file": "catbus_scripts/volunteer_schedule_dashboard.html",
      "source_location": "line 5: <?!= include('shared_styles') ?>",
      "weight": 1.0
    },
    {
      "source": "volunteer_signinout_ui",
      "target": "shared_styles_catbus_theme",
      "relation": "references",
      "confidence": "EXTRACTED",
      "confidence_score": 1.0,
      "source_file": "catbus_scripts/volunteer_signinout.html",
      "source_location": "line 5: <?!= include('shared_styles') ?>",
      "weight": 1.0
    },
    {
      "source": "volunteer_dashboard_ui",
      "target": "concept_shared_scripts",
      "relation": "references",
      "confidence": "EXTRACTED",
      "confidence_score": 1.0,
      "source_file": "catbus_scripts/volunteer_dashboard.html",
      "source_location": "line 613: <?!= include('shared_scripts') ?>",
      "weight": 1.0
    },
    {
      "source": "volunteer_schedule_dashboard_ui",
      "target": "concept_shared_scripts",
      "relation": "references",
      "confidence": "EXTRACTED",
      "confidence_score": 1.0,
      "source_file": "catbus_scripts/volunteer_schedule_dashboard.html",
      "source_location": "line 436: <?!= include('shared_scripts') ?>",
      "weight": 1.0
    },
    {
      "source": "volunteer_signinout_ui",
      "target": "concept_shared_scripts",
      "relation": "references",
      "confidence": "EXTRACTED",
      "confidence_score": 1.0,
      "source_file": "catbus_scripts/volunteer_signinout.html",
      "source_location": "line 414: <?!= include('shared_scripts') ?>",
      "weight": 1.0
    },
    {
      "source": "stats_dashboard_ui",
      "target": "concept_shared_scripts",
      "relation": "references",
      "confidence": "EXTRACTED",
      "confidence_score": 1.0,
      "source_file": "catbus_scripts/stats_dashboard.html",
      "source_location": "line 519: <?!= include('shared_scripts') ?>",
      "weight": 1.0
    },
    {
      "source": "volunteer_management_ui",
      "target": "concept_password_gate",
      "relation": "references",
      "confidence": "EXTRACTED",
      "confidence_score": 1.0,
      "source_file": "catbus_scripts/volunteer_management.html",
      "source_location": "line 167: <?!= include('_PasswordGate') ?>",
      "weight": 1.0
    },
    {
      "source": "stats_dashboard_ui",
      "target": "backend_getAdminDashboardData",
      "relation": "calls",
      "confidence": "EXTRACTED",
      "confidence_score": 1.0,
      "source_file": "catbus_scripts/stats_dashboard.html",
      "source_location": "line 1015: .getAdminDashboardData(selectedDate)",
      "weight": 1.0
    },
    {
      "source": "volunteer_dashboard_ui",
      "target": "backend_getAllVolunteerNames",
      "relation": "calls",
      "confidence": "EXTRACTED",
      "confidence_score": 1.0,
      "source_file": "catbus_scripts/volunteer_dashboard.html",
      "source_location": "loadVolunteerNames()",
      "weight": 1.0
    },
    {
      "source": "volunteer_dashboard_ui",
      "target": "backend_getScheduleConfig",
      "relation": "calls",
      "confidence": "EXTRACTED",
      "confidence_score": 1.0,
      "source_file": "catbus_scripts/volunteer_dashboard.html",
      "source_location": "loadScheduleConfig()",
      "weight": 1.0
    },
    {
      "source": "volunteer_dashboard_ui",
      "target": "backend_getVolunteerScheduleByName",
      "relation": "calls",
      "confidence": "EXTRACTED",
      "confidence_score": 1.0,
      "source_file": "catbus_scripts/volunteer_dashboard.html",
      "source_location": "searchByName()",
      "weight": 1.0
    },
    {
      "source": "volunteer_dashboard_ui",
      "target": "backend_getVolunteerPersonalStats",
      "relation": "calls",
      "confidence": "EXTRACTED",
      "confidence_score": 1.0,
      "source_file": "catbus_scripts/volunteer_dashboard.html",
      "source_location": "refreshStats()",
      "weight": 1.0
    },
    {
      "source": "volunteer_dashboard_ui",
      "target": "backend_getVolunteerCredentialStatus",
      "relation": "calls",
      "confidence": "EXTRACTED",
      "confidence_score": 1.0,
      "source_file": "catbus_scripts/volunteer_dashboard.html",
      "source_location": "loadCredentialStatus()",
      "weight": 1.0
    },
    {
      "source": "volunteer_dashboard_ui",
      "target": "backend_submitVolunteerCredentials",
      "relation": "calls",
      "confidence": "EXTRACTED",
      "confidence_score": 1.0,
      "source_file": "catbus_scripts/volunteer_dashboard.html",
      "source_location": "submitCredentials()",
      "weight": 1.0
    },
    {
      "source": "volunteer_dashboard_ui",
      "target": "backend_getVolunteerProductKeys",
      "relation": "calls",
      "confidence": "EXTRACTED",
      "confidence_score": 1.0,
      "source_file": "catbus_scripts/volunteer_dashboard.html",
      "source_location": "loadCredentialStatus()",
      "weight": 1.0
    },
    {
      "source": "volunteer_management_ui",
      "target": "backend_getAcceptedApplications",
      "relation": "calls",
      "confidence": "EXTRACTED",
      "confidence_score": 1.0,
      "source_file": "catbus_scripts/volunteer_management.html",
      "source_location": "loadAccepted()",
      "weight": 1.0
    },
    {
      "source": "volunteer_management_ui",
      "target": "backend_transferToConsolidatedList",
      "relation": "calls",
      "confidence": "EXTRACTED",
      "confidence_score": 1.0,
      "source_file": "catbus_scripts/volunteer_management.html",
      "source_location": "transferSelected()",
      "weight": 1.0
    },
    {
      "source": "volunteer_management_ui",
      "target": "backend_getVolunteerManagementData",
      "relation": "calls",
      "confidence": "EXTRACTED",
      "confidence_score": 1.0,
      "source_file": "catbus_scripts/volunteer_management.html",
      "source_location": "loadRoster()",
      "weight": 1.0
    },
    {
      "source": "volunteer_management_ui",
      "target": "backend_getNoShowVolunteers",
      "relation": "calls",
      "confidence": "EXTRACTED",
      "confidence_score": 1.0,
      "source_file": "catbus_scripts/volunteer_management.html",
      "source_location": "loadNoShows()",
      "weight": 1.0
    },
    {
      "source": "volunteer_management_ui",
      "target": "backend_updateVolunteerRolesBatch",
      "relation": "calls",
      "confidence": "EXTRACTED",
      "confidence_score": 1.0,
      "source_file": "catbus_scripts/volunteer_management.html",
      "source_location": "markSelectedDrop()",
      "weight": 1.0
    },
    {
      "source": "volunteer_management_ui",
      "target": "backend_getUnmatchedVolunteerNames",
      "relation": "calls",
      "confidence": "EXTRACTED",
      "confidence_score": 1.0,
      "source_file": "catbus_scripts/volunteer_management.html",
      "source_location": "loadUnmatched()",
      "weight": 1.0
    },
    {
      "source": "volunteer_management_ui",
      "target": "backend_getAlumniData",
      "relation": "calls",
      "confidence": "EXTRACTED",
      "confidence_score": 1.0,
      "source_file": "catbus_scripts/volunteer_management.html",
      "source_location": "loadAlumni()",
      "weight": 1.0
    },
    {
      "source": "volunteer_management_ui",
      "target": "backend_setVolunteerBlacklist",
      "relation": "calls",
      "confidence": "EXTRACTED",
      "confidence_score": 1.0,
      "source_file": "catbus_scripts/volunteer_management.html",
      "source_location": "toggleBlacklist()",
      "weight": 1.0
    },
    {
      "source": "volunteer_schedule_dashboard_ui",
      "target": "backend_getScheduleConfig",
      "relation": "calls",
      "confidence": "EXTRACTED",
      "confidence_score": 1.0,
      "source_file": "catbus_scripts/volunteer_schedule_dashboard.html",
      "source_location": "loadScheduleConfig()",
      "weight": 1.0
    },
    {
      "source": "volunteer_schedule_dashboard_ui",
      "target": "backend_getVolunteerScheduleByDay",
      "relation": "calls",
      "confidence": "EXTRACTED",
      "confidence_score": 1.0,
      "source_file": "catbus_scripts/volunteer_schedule_dashboard.html",
      "source_location": "viewDaySchedule()",
      "weight": 1.0
    },
    {
      "source": "volunteer_schedule_dashboard_ui",
      "target": "backend_getVolunteerDistribution",
      "relation": "calls",
      "confidence": "EXTRACTED",
      "confidence_score": 1.0,
      "source_file": "catbus_scripts/volunteer_schedule_dashboard.html",
      "source_location": "viewDistribution()",
      "weight": 1.0
    },
    {
      "source": "volunteer_signinout_ui",
      "target": "backend_getConsolidatedVolunteerData",
      "relation": "calls",
      "confidence": "EXTRACTED",
      "confidence_score": 1.0,
      "source_file": "catbus_scripts/volunteer_signinout.html",
      "source_location": "loadVolunteerData()",
      "weight": 1.0
    },
    {
      "source": "volunteer_signinout_ui",
      "target": "backend_getAvailableStations",
      "relation": "calls",
      "confidence": "EXTRACTED",
      "confidence_score": 1.0,
      "source_file": "catbus_scripts/volunteer_signinout.html",
      "source_location": "loadAvailableStations()",
      "weight": 1.0
    },
    {
      "source": "volunteer_signinout_ui",
      "target": "backend_getActiveSessions",
      "relation": "calls",
      "confidence": "EXTRACTED",
      "confidence_score": 1.0,
      "source_file": "catbus_scripts/volunteer_signinout.html",
      "source_location": "loadActiveSessions()",
      "weight": 1.0
    },
    {
      "source": "volunteer_signinout_ui",
      "target": "backend_getSignInStats",
      "relation": "calls",
      "confidence": "EXTRACTED",
      "confidence_score": 1.0,
      "source_file": "catbus_scripts/volunteer_signinout.html",
      "source_location": "refreshStats()",
      "weight": 1.0
    },
    {
      "source": "volunteer_signinout_ui",
      "target": "backend_signInVolunteer",
      "relation": "calls",
      "confidence": "EXTRACTED",
      "confidence_score": 1.0,
      "source_file": "catbus_scripts/volunteer_signinout.html",
      "source_location": "handleSignIn()",
      "weight": 1.0
    },
    {
      "source": "volunteer_signinout_ui",
      "target": "backend_signOutVolunteer",
      "relation": "calls",
      "confidence": "EXTRACTED",
      "confidence_score": 1.0,
      "source_file": "catbus_scripts/volunteer_signinout.html",
      "source_location": "handleSignOut()",
      "weight": 1.0
    },
    {
      "source": "webpage_faq",
      "target": "webpage_appointment_screening",
      "relation": "references",
      "confidence": "EXTRACTED",
      "confidence_score": 1.0,
      "source_file": "webpage/FAQ.html",
      "source_location": "faq-screening-p: link to appointment_screening.html",
      "weight": 1.0
    },
    {
      "source": "webpage_faq",
      "target": "webpage_postfiling",
      "relation": "references",
      "confidence": "EXTRACTED",
      "confidence_score": 1.0,
      "source_file": "webpage/FAQ.html",
      "source_location": "rent receipt link to /PostFiling.html",
      "weight": 1.0
    },
    {
      "source": "webpage_index",
      "target": "webpage_appointment_screening",
      "relation": "references",
      "confidence": "EXTRACTED",
      "confidence_score": 1.0,
      "source_file": "webpage/index.html",
      "source_location": "booking-walkin-p: link to appointment_screening.html",
      "weight": 1.0
    },
    {
      "source": "webpage_index",
      "target": "webpage_checklist",
      "relation": "references",
      "confidence": "EXTRACTED",
      "confidence_score": 1.0,
      "source_file": "webpage/index.html",
      "source_location": "Checklist PDF link and checklist.html reference",
      "weight": 1.0
    },
    {
      "source": "webpage_catbus",
      "target": "concept_catbus_config_js",
      "relation": "references",
      "confidence": "EXTRACTED",
      "confidence_score": 1.0,
      "source_file": "webpage/catbus.html",
      "source_location": "<script src=\"config.js\"> and CATBUS_CONFIG.WEBAPP_URL usage",
      "weight": 1.0
    },
    {
      "source": "webpage_catbus",
      "target": "concept_webapp_router",
      "relation": "references",
      "confidence": "EXTRACTED",
      "confidence_score": 1.0,
      "source_file": "webpage/catbus.html",
      "source_location": "?app=intake, ?app=queue, ?app=control, ?app=alerts, ?app=admin, ?app=volunteer, ?app=schedule, ?app=availability",
      "weight": 1.0
    },
    {
      "source": "webpage_admin",
      "target": "concept_catbus_config_js",
      "relation": "references",
      "confidence": "EXTRACTED",
      "confidence_score": 1.0,
      "source_file": "webpage/admin.html",
      "source_location": "<script src=\"config.js\"> and CATBUS_CONFIG.WEBAPP_URL usage",
      "weight": 1.0
    },
    {
      "source": "webpage_admin",
      "target": "concept_webapp_router",
      "relation": "references",
      "confidence": "EXTRACTED",
      "confidence_score": 1.0,
      "source_file": "webpage/admin.html",
      "source_location": "?app=signin, ?app=assignment, ?app=productcodes, ?app=quizreview, ?app=appreviewer, ?app=archive, ?app=raffledraw, ?app=massemail, ?app=volunteermgmt",
      "weight": 1.0
    },
    {
      "source": "webpage_feedback",
      "target": "concept_catbus_config_js",
      "relation": "references",
      "confidence": "EXTRACTED",
      "confidence_score": 1.0,
      "source_file": "webpage/feedback.html",
      "source_location": "<script src=\"config.js\"> and CATBUS_CONFIG.WEBAPP_URL",
      "weight": 1.0
    },
    {
      "source": "webpage_feedback",
      "target": "concept_webapp_router",
      "relation": "calls",
      "confidence": "EXTRACTED",
      "confidence_score": 1.0,
      "source_file": "webpage/feedback.html",
      "source_location": "fetch(APPS_SCRIPT_URL + '?action=feedback')",
      "weight": 1.0
    },
    {
      "source": "webpage_volunteer_feedback",
      "target": "concept_catbus_config_js",
      "relation": "references",
      "confidence": "EXTRACTED",
      "confidence_score": 1.0,
      "source_file": "webpage/volunteer_feedback.html",
      "source_location": "<script src=\"config.js\"> and CATBUS_CONFIG.WEBAPP_URL",
      "weight": 1.0
    },
    {
      "source": "webpage_volunteer_feedback",
      "target": "concept_webapp_router",
      "relation": "calls",
      "confidence": "EXTRACTED",
      "confidence_score": 1.0,
      "source_file": "webpage/volunteer_feedback.html",
      "source_location": "fetch(APPS_SCRIPT_URL + '?action=volunteerFeedback')",
      "weight": 1.0
    },
    {
      "source": "webpage_volunteerapplications",
      "target": "concept_catbus_config_js",
      "relation": "references",
      "confidence": "EXTRACTED",
      "confidence_score": 1.0,
      "source_file": "webpage/volunteerapplications.html",
      "source_location": "<script src=\"config.js\"> and CATBUS_CONFIG.WEBAPP_URL",
      "weight": 1.0
    },
    {
      "source": "webpage_volunteerapplications",
      "target": "concept_webapp_router",
      "relation": "calls",
      "confidence": "EXTRACTED",
      "confidence_score": 1.0,
      "source_file": "webpage/volunteerapplications.html",
      "source_location": "fetch(APPS_SCRIPT_URL, ...) POST requests",
      "weight": 1.0
    },
    {
      "source": "webpage_training",
      "target": "concept_catbus_config_js",
      "relation": "references",
      "confidence": "EXTRACTED",
      "confidence_score": 1.0,
      "source_file": "webpage/training.html",
      "source_location": "<script src=\"config.js\"> and ?app=quiz link rewrite",
      "weight": 1.0
    },
    {
      "source": "webpage_training",
      "target": "concept_webapp_router",
      "relation": "references",
      "confidence": "EXTRACTED",
      "confidence_score": 1.0,
      "source_file": "webpage/training.html",
      "source_location": "?app=quiz Quiz Submission link",
      "weight": 1.0
    },
    {
      "source": "webpage_search",
      "target": "webpage_index",
      "relation": "references",
      "confidence": "INFERRED",
      "confidence_score": 0.7,
      "source_file": "webpage/search.html",
      "source_location": "SEARCH_INDEX references site pages",
      "weight": 0.7
    },
    {
      "source": "appsscript_json_config",
      "target": "concept_google_oauth_scopes",
      "relation": "implements",
      "confidence": "EXTRACTED",
      "confidence_score": 1.0,
      "source_file": "catbus_scripts/appsscript.json",
      "source_location": "oauthScopes array",
      "weight": 1.0
    },
    {
      "source": "appsscript_json_config",
      "target": "concept_webapp_router",
      "relation": "implements",
      "confidence": "EXTRACTED",
      "confidence_score": 1.0,
      "source_file": "catbus_scripts/appsscript.json",
      "source_location": "webapp.access=ANYONE_ANONYMOUS, executeAs=USER_DEPLOYING",
      "weight": 1.0
    },
    {
      "source": "volunteer_management_ui",
      "target": "concept_volunteer_roles",
      "relation": "references",
      "confidence": "EXTRACTED",
      "confidence_score": 1.0,
      "source_file": "catbus_scripts/volunteer_management.html",
      "source_location": "role-pill CSS classes: mentor, filer, frontline, drop, blacklisted",
      "weight": 1.0
    },
    {
      "source": "volunteer_management_ui",
      "target": "concept_alumni_blacklist",
      "relation": "implements",
      "confidence": "EXTRACTED",
      "confidence_score": 1.0,
      "source_file": "catbus_scripts/volunteer_management.html",
      "source_location": "Section E: Volunteer Alumni & Blacklist",
      "weight": 1.0
    },
    {
      "source": "webpage_appointment_screening",
      "target": "concept_eligibility_screening",
      "relation": "implements",
      "confidence": "EXTRACTED",
      "confidence_score": 1.0,
      "source_file": "webpage/appointment_screening.html",
      "source_location": "inline booking form with eligibility/complexity logic",
      "weight": 1.0
    },
    {
      "source": "webpage_index",
      "target": "concept_eligibility_screening",
      "relation": "references",
      "confidence": "EXTRACTED",
      "confidence_score": 1.0,
      "source_file": "webpage/index.html",
      "source_location": "Eligibility section with income table and ineligible list",
      "weight": 1.0
    },
    {
      "source": "webpage_faq",
      "target": "concept_eligibility_screening",
      "relation": "references",
      "confidence": "EXTRACTED",
      "confidence_score": 1.0,
      "source_file": "webpage/FAQ.html",
      "source_location": "FAQ items referencing eligibility (self-employment, Uber/DoorDash)",
      "weight": 1.0
    },
    {
      "source": "logo_afsa",
      "target": "webpage_appointment_screening",
      "relation": "references",
      "confidence": "EXTRACTED",
      "confidence_score": 1.0,
      "source_file": "webpage/appointment_screening.html",
      "source_location": "header img tag in appointment_screening.html",
      "weight": 1.0
    },
    {
      "source": "volunteer_dashboard_ui",
      "target": "concept_volunteer_roles",
      "relation": "references",
      "confidence": "EXTRACTED",
      "confidence_score": 1.0,
      "source_file": "catbus_scripts/volunteer_dashboard.html",
      "source_location": "role-badge CSS classes: mentor, frontline, filer, internalservices",
      "weight": 1.0
    },
    {
      "source": "volunteer_schedule_dashboard_ui",
      "target": "concept_volunteer_roles",
      "relation": "references",
      "confidence": "EXTRACTED",
      "confidence_score": 1.0,
      "source_file": "catbus_scripts/volunteer_schedule_dashboard.html",
      "source_location": "filterRole dropdown: Mentor, Frontline, Filer, Internal Services",
      "weight": 1.0
    },
    {
      "source": "volunteer_signinout_ui",
      "target": "concept_volunteer_roles",
      "relation": "references",
      "confidence": "EXTRACTED",
      "confidence_score": 1.0,
      "source_file": "catbus_scripts/volunteer_signinout.html",
      "source_location": "selectVolunteer() role->station mapping",
      "weight": 1.0
    },
    {
      "source": "webpage_catbus",
      "target": "volunteer_signinout_ui",
      "relation": "references",
      "confidence": "EXTRACTED",
      "confidence_score": 1.0,
      "source_file": "webpage/catbus.html",
      "source_location": "?app=signin tool card",
      "weight": 1.0
    },
    {
      "source": "webpage_catbus",
      "target": "volunteer_schedule_dashboard_ui",
      "relation": "references",
      "confidence": "EXTRACTED",
      "confidence_score": 1.0,
      "source_file": "webpage/catbus.html",
      "source_location": "?app=schedule tool card",
      "weight": 1.0
    },
    {
      "source": "webpage_catbus",
      "target": "volunteer_dashboard_ui",
      "relation": "references",
      "confidence": "EXTRACTED",
      "confidence_score": 1.0,
      "source_file": "webpage/catbus.html",
      "source_location": "?app=volunteer tool card",
      "weight": 1.0
    },
    {
      "source": "webpage_catbus",
      "target": "stats_dashboard_ui",
      "relation": "references",
      "confidence": "EXTRACTED",
      "confidence_score": 1.0,
      "source_file": "webpage/catbus.html",
      "source_location": "?app=admin Stats Dashboard tool card",
      "weight": 1.0
    },
    {
      "source": "webpage_admin",
      "target": "volunteer_management_ui",
      "relation": "references",
      "confidence": "EXTRACTED",
      "confidence_score": 1.0,
      "source_file": "webpage/admin.html",
      "source_location": "?app=volunteermgmt tool card",
      "weight": 1.0
    },
    {
      "source": "webpage_volunteer_feedback",
      "target": "webpage_volunteerapplications",
      "relation": "semantically_similar_to",
      "confidence": "INFERRED",
      "confidence_score": 0.65,
      "source_file": "webpage/volunteer_feedback.html",
      "source_location": null,
      "weight": 0.65
    },
    {
      "source": "webpage_feedback",
      "target": "webpage_volunteer_feedback",
      "relation": "semantically_similar_to",
      "confidence": "INFERRED",
      "confidence_score": 0.8,
      "source_file": "webpage/feedback.html",
      "source_location": "both collect post-clinic feedback via CATBUS_CONFIG.WEBAPP_URL fetch",
      "weight": 0.8
    },
    {
      "source": "volunteer_dashboard_ui",
      "target": "volunteer_signinout_ui",
      "relation": "semantically_similar_to",
      "confidence": "INFERRED",
      "confidence_score": 0.7,
      "source_file": "catbus_scripts/volunteer_dashboard.html",
      "source_location": "both present volunteer-facing interfaces with autocomplete name search",
      "weight": 0.7
    },
    {
      "source": "stats_dashboard_ui",
      "target": "volunteer_dashboard_ui",
      "relation": "semantically_similar_to",
      "confidence": "INFERRED",
      "confidence_score": 0.65,
      "source_file": "catbus_scripts/stats_dashboard.html",
      "source_location": "both display volunteer performance statistics",
      "weight": 0.65
    },
    {
      "source": "webpage_about",
      "target": "webpage_index",
      "relation": "semantically_similar_to",
      "confidence": "INFERRED",
      "confidence_score": 0.7,
      "source_file": "webpage/about.html",
      "source_location": "both are public-facing informational pages about the tax clinic",
      "weight": 0.7
    },
    {
      "source": "webpage_checklist",
      "target": "webpage_index",
      "relation": "references",
      "confidence": "INFERRED",
      "confidence_score": 0.8,
      "source_file": "webpage/index.html",
      "source_location": "index.html links to checklist PDF from same source as checklist.html",
      "weight": 0.8
    },
    {
      "source": "volunteer_management_ui",
      "target": "volunteer_schedule_dashboard_ui",
      "relation": "semantically_similar_to",
      "confidence": "INFERRED",
      "confidence_score": 0.6,
      "source_file": "catbus_scripts/volunteer_management.html",
      "source_location": "both manage volunteer roster data from Consolidated Volunteer List",
      "weight": 0.6
    }
  ],
  "hyperedges": [
    {
      "id": "catbus_ui_shared_styles_system",
      "label": "CATBUS HtmlService Pages Using Shared Styles",
      "nodes": [
        "shared_styles_catbus_theme",
        "stats_dashboard_ui",
        "volunteer_dashboard_ui",
        "volunteer_schedule_dashboard_ui",
        "volunteer_signinout_ui"
      ],
      "relation": "implement",
      "confidence": "EXTRACTED",
      "confidence_score": 1.0,
      "source_file": "catbus_scripts/shared_styles.html"
    },
    {
      "id": "public_webpage_eligibility_cluster",
      "label": "Public Pages Conveying Eligibility Information",
      "nodes": [
        "webpage_index",
        "webpage_faq",
        "webpage_appointment_screening",
        "concept_eligibility_screening"
      ],
      "relation": "participate_in",
      "confidence": "EXTRACTED",
      "confidence_score": 0.95,
      "source_file": "webpage/index.html"
    },
    {
      "id": "volunteer_lifecycle_pages",
      "label": "Volunteer Lifecycle Workflow Pages",
      "nodes": [
        "webpage_volunteerapplications",
        "volunteer_management_ui",
        "volunteer_signinout_ui",
        "volunteer_schedule_dashboard_ui",
        "volunteer_dashboard_ui",
        "webpage_volunteer_feedback"
      ],
      "relation": "participate_in",
      "confidence": "INFERRED",
      "confidence_score": 0.85,
      "source_file": "catbus_scripts/volunteer_management.html"
    },
    {
      "id": "webapp_url_config_consumers",
      "label": "Static Webpage Files Using CATBUS_CONFIG.WEBAPP_URL",
      "nodes": [
        "concept_catbus_config_js",
        "webpage_catbus",
        "webpage_admin",
        "webpage_feedback",
        "webpage_volunteer_feedback",
        "webpage_volunteerapplications",
        "webpage_training"
      ],
      "relation": "implement",
      "confidence": "EXTRACTED",
      "confidence_score": 1.0,
      "source_file": "webpage/catbus.html"
    },
    {
      "id": "apps_script_oauth_resources",
      "label": "Apps Script OAuth Scopes (Spreadsheets, Drive, Gmail, External)",
      "nodes": [
        "appsscript_json_config",
        "concept_google_oauth_scopes",
        "concept_webapp_router"
      ],
      "relation": "implement",
      "confidence": "EXTRACTED",
      "confidence_score": 1.0,
      "source_file": "catbus_scripts/appsscript.json"
    },
    {
      "id": "client_facing_info_pages",
      "label": "Client-Facing Informational Pages",
      "nodes": [
        "webpage_index",
        "webpage_faq",
        "webpage_about",
        "webpage_checklist",
        "webpage_postfiling",
        "webpage_search"
      ],
      "relation": "participate_in",
      "confidence": "INFERRED",
      "confidence_score": 0.85,
      "source_file": "webpage/index.html"
    }
  ],
  "input_tokens": 0,
  "output_tokens": 0
}
